{
    "version": 3,
    "vendor": {
        "conan": {}
    },
    "cmakeMinimumRequired": {
        "major": 3,
        "minor": 15,
        "patch": 0
    },
    "configurePresets": [
        {
            "name": "conan-release",
            "displayName": "'conan-release' config",
            "description": "'conan-release' configure using 'Unix Makefiles' generator",
            "generator": "Unix Makefiles",
            "cacheVariables": {
                "CMAKE_POLICY_DEFAULT_CMP0091": "NEW",
                "CMAKE_BUILD_TYPE": "Release"
            },
            "environment": {
                "PATH": "/Users/jacobrunge/.conan2/p/cmake3abd806e43ff1/p/CMake.app/Contents/bin:$penv{PATH}"
            },
            "cmakeExecutable": "/Users/jacobrunge/.conan2/p/cmake3abd806e43ff1/p/CMake.app/Contents/bin/cmake",
            "toolchainFile": "generators/conan_toolchain.cmake",
            "binaryDir": "/Users/jacobrunge/Code/cpp_tut/build/Release"
        }
    ],
    "buildPresets": [
        {
            "name": "conan-release",
            "configurePreset": "conan-release",
            "jobs": 12
        }
    ],
    "testPresets": [
        {
            "name": "conan-release",
            "configurePreset": "conan-release"
        }
    ]
}